blob_mounting_helper_utility/__init__.py
blob_mounting_helper_utility/utils.py
blob_mounting_helper_utility-1.1.4.dist-info/METADATA
blob_mounting_helper_utility-1.1.4.dist-info/WHEEL
blob_mounting_helper_utility-1.1.4.dist-info/top_level.txt
blob_mounting_helper_utility-1.1.4.dist-info/RECORD
