Metadata-Version: 2.1
Name: blob-mounting-helper-utility
Version: 1.1.4
Summary: Blob mapping utility for easy translation between azure urls and local paths
Home-page: UNKNOWN
Author: Ivica Matic
Author-email: <ivica.matic@spatialdays.com>
License: UNKNOWN
Keywords: python,azure,blob,mount
Platform: UNKNOWN
Classifier: Development Status :: 1 - Planning
Classifier: Intended Audience :: Developers
Classifier: Programming Language :: Python :: 3
Classifier: Operating System :: Unix
Requires-Dist: azure-storage-blob (==12.17.0)
